iac_validate/__init__.py
iac_validate/__main__.py
iac_validate/ansible_vault.py
iac_validate/cli/__init__.py
iac_validate/cli/main.py
iac_validate/cli/options.py
iac_validate/validator.py
iac_validate/yaml.py
iac_validate-0.2.7.dist-info/LICENSE
iac_validate-0.2.7.dist-info/METADATA
iac_validate-0.2.7.dist-info/WHEEL
iac_validate-0.2.7.dist-info/entry_points.txt
iac_validate-0.2.7.dist-info/RECORD
