Metadata-Version: 2.3
Name: iac-validate
Version: 0.2.7
Summary: A CLI tool to perform syntactic and semantic validation of YAML files.
Home-page: https://github.com/netascode/iac-validate
License: LICENSE
Author: Daniel Schmidt
Author-email: danischm@cisco.com
Maintainer: Daniel Schmidt
Maintainer-email: danischm@cisco.com
Requires-Python: >=3.10,<4.0
Classifier: License :: Other/Proprietary License
Classifier: Programming Language :: Python :: 3
Classifier: Programming Language :: Python :: 3.10
Classifier: Programming Language :: Python :: 3.11
Classifier: Programming Language :: Python :: 3.12
Classifier: Programming Language :: Python :: 3.13
Requires-Dist: click (>=8.0.4,<9.0.0)
Requires-Dist: errorhandler (>=2.0.1,<3.0.0)
Requires-Dist: ruamel-yaml (>0.16.10)
Requires-Dist: yamale (>=4.0.3,<5.0.0)
Project-URL: Documentation, https://github.com/netascode/iac-validate
Project-URL: Repository, https://github.com/netascode/iac-validate
